CHANGES.rst
LICENSE.txt
MANIFEST.in
README.rst
setup.py
djinga/__init__.py
djinga/compat.py
djinga/environment.py
djinga/register.py
djinga/template.py
djinga/version.py
djinga.egg-info/PKG-INFO
djinga.egg-info/SOURCES.txt
djinga.egg-info/dependency_links.txt
djinga.egg-info/requires.txt
djinga.egg-info/top_level.txt
djinga.egg-info/zip-safe
djinga/backends/__init__.py
djinga/backends/djinga.py
djinga/ext/__init__.py
djinga/ext/_base.py
djinga/ext/djangotags.py
djinga/ext/files.py
djinga/ext/htmlcompress.py
djinga/ext/urls.py
djinga/management/__init__.py
djinga/management/commands/__init__.py
djinga/management/commands/makemessages.py
djinga/templatetags/__init__.py
djinga/templatetags/djinga_tags.py