Metadata-Version: 1.1
Name: djinga
Version: 2.1.2
Summary: Unobtrusive jinja2 integration in Django
Home-page: https://bitbucket.org/tkhyn/djinga
Author: Thomas Khyn
Author-email: thomas@ksytek.com
License: UNKNOWN
Keywords: django,jinja2
Platform: UNKNOWN
Classifier: Programming Language :: Python
Classifier: Programming Language :: Python :: 2
Classifier: Programming Language :: Python :: 3
Classifier: License :: OSI Approved :: MIT License
Classifier: License :: OSI Approved :: BSD License
Classifier: Operating System :: OS Independent
Classifier: Development Status :: 5 - Production/Stable
Classifier: Intended Audience :: Developers
Classifier: Framework :: Django
Classifier: Environment :: Other Environment
Classifier: Topic :: Software Development
Classifier: Topic :: Text Editors :: Text Processing
